license.txt
design_by_contract/__init__.py
design_by_contract/py.typed
design_by_contract-0.3.1.dist-info/WHEEL
design_by_contract-0.3.1.dist-info/METADATA
design_by_contract-0.3.1.dist-info/RECORD
