Metadata-Version: 2.1
Name: design-by-contract
Version: 0.3.1
Summary: Handy decorator to define contracts with dependency injection in Python 3.10 and above
Home-page: https://github.com/StefanUlbrich/design-by-contract
License: MIT
Author: Stefan Ulbrich
Requires-Python: >=3.10,<4.0
Classifier: Development Status :: 3 - Alpha
Classifier: Intended Audience :: Developers
Classifier: License :: OSI Approved :: MIT License
Classifier: Programming Language :: Python :: 3
Classifier: Programming Language :: Python :: 3.10
Classifier: Topic :: Software Development :: Documentation
Classifier: Topic :: Software Development :: Quality Assurance
Project-URL: Repository, https://github.com/StefanUlbrich/design-by-contract
